delpinos/api/app.py
delpinos/api/core/config.py
delpinos/api/core/controllers/__init__.py
delpinos/api/core/controllers/api_controller.py
delpinos/api/core/controllers/api_controller_abstract.py
delpinos/api/core/controllers/enqueue_controller.py
delpinos/api/core/encoders/__init__.py
delpinos/api/core/encoders/api_encoder.py
delpinos/api/core/encoders/api_encoder_abstract.py
delpinos/api/core/encoders/json_encoder.py
delpinos/api/core/encoders/raw_encoder.py
delpinos/api/core/encoders/text_encoder.py
delpinos/api/core/exceptions/api_exception.py
delpinos/api/core/exceptions/badrequest_exception.py
delpinos/api/core/exceptions/forbidden_exception.py
delpinos/api/core/exceptions/integration_exception.py
delpinos/api/core/exceptions/notfound_exception.py
delpinos/api/core/exceptions/persistence_exception.py
delpinos/api/core/exceptions/unauthorized_exception.py
delpinos/api/core/exceptions/validate_exception.py
delpinos/api/core/factories/api_factory.py
delpinos/api/core/factories/api_factory_abstract.py
delpinos/api/core/requests/__init__.py
delpinos/api/core/requests/api_request.py
delpinos/api/core/requests/api_request_abstract.py
delpinos/api/core/responses/__init__.py
delpinos/api/core/responses/api_response.py
delpinos/api/core/responses/api_response_abstract.py
delpinos/core/config_object.py
delpinos/core/config_object_abstract.py
delpinos/core/container.py
delpinos/core/container_abstract.py
delpinos/core/decorators/trigger_decorator.py
delpinos/core/encoders/__init__.py
delpinos/core/encoders/encoder_abstract.py
delpinos/core/encoders/json_encoder.py
delpinos/core/encoders/raw_encoder.py
delpinos/core/encoders/text_encoder.py
delpinos/core/exceptions/api_integration_exception.py
delpinos/core/exceptions/badrequest_exception.py
delpinos/core/exceptions/base_exception.py
delpinos/core/exceptions/forbidden_exception.py
delpinos/core/exceptions/integration_exception.py
delpinos/core/exceptions/notfound_exception.py
delpinos_core-0.0.3.dist-info/METADATA
delpinos_core-0.0.3.dist-info/WHEEL
delpinos_core-0.0.3.dist-info/top_level.txt
delpinos_core-0.0.3.dist-info/RECORD
