Metadata-Version: 2.1
Name: delpinos-core
Version: 0.0.3
Summary: Base codes - Delpinos Framework
Author-email: Alef Bruno Delpino de Oliveira <alef@delpinos.com>
Keywords: delpinos,framework,core
Classifier: Programming Language :: Python :: 3
Classifier: Programming Language :: Python :: 3.10
Classifier: Topic :: Software Development :: Libraries :: Python Modules
Requires-Python: >=3.10
Requires-Dist: requests >=2.31.0
Requires-Dist: pydantic >=2.5.1
Requires-Dist: pydantic-core >=2.14.3
